{
  "updated_at": "2026-07-08",
  "currency": "CNY",
  "draft": false,
  "categories": {
    "kb": {
      "label": "矮軸鍵盤",
      "spec_fields": [
        "连接方式",
        "按键数",
        "按键类型",
        "按键行程",
        "按键寿命",
        "供电续航"
      ],
      "items": [
        {
          "brand": "珂芝 KZZI",
          "model": "i75青春版",
          "price": 299,
          "size": "327.5*150.7*30.3 mm",
          "weight": "710 g",
          "specs_detail": {
            "连接方式": "蓝牙/2.4G/有线 三模",
            "按键数": "87键(75%配列)",
            "按键类型": "矮轴(白雪轴),全键热插拔",
            "按键行程": "—",
            "按键寿命": "—",
            "供电续航": "—"
          },
          "sell": "",
          "image": "images/kzzi-i75-youth.jpg",
          "source_url": "https://diy.zol.com.cn/1009/10093646.html",
          "rating": null,
          "reviews": null,
          "launched": "2025"
        },
        {
          "brand": "Keychron",
          "model": "J9 Ultra",
          "price": 339,
          "size": "315.2×132.7×12 mm",
          "weight": "约630 g",
          "specs_detail": {
            "连接方式": "蓝牙5.2/2.4G 8KHz/有线 三模",
            "按键数": "84键(75%配列)",
            "按键类型": "Keychron Milk POM矮轴(红/棕/香蕉 可选)",
            "按键行程": "总程3.1mm/触发1.3mm",
            "按键寿命": "—",
            "供电续航": "2000mAh,关灯最长635小时"
          },
          "sell": "",
          "image": "images/keychron-j9-ultra.jpg",
          "source_url": "https://www.keychron.com/products/keychron-j9-ultra-wireless-mechanical-keyboard",
          "rating": null,
          "reviews": null,
          "launched": "2026"
        },
        {
          "brand": "洛斐 Lofree",
          "model": "小順青春版",
          "price": 399,
          "size": "316.8*138*23.5 mm",
          "weight": "550 g",
          "specs_detail": {
            "连接方式": "蓝牙5.4/2.4G/有线 三模",
            "按键数": "84键",
            "按键类型": "凯华x洛斐 全POM矮轴(轻灵轴)",
            "按键行程": "全程2.8mm/触发1.2mm",
            "按键寿命": "5000万次",
            "供电续航": "2000mAh,关灯约80小时"
          },
          "sell": "",
          "image": "https://cdn.shopify.com/s/files/1/2779/9046/files/Flow84_Marble_PI01.webp",
          "source_url": "https://www.lofree.co/products/flow-lite84-mechanical-keyboard",
          "rating": null,
          "reviews": null,
          "launched": "2024"
        },
        {
          "brand": "AKKO",
          "model": "Air 01",
          "price": 399,
          "size": "319×131×21 mm",
          "weight": "约612 g",
          "specs_detail": {
            "连接方式": "蓝牙5.0/2.4G/有线 三模",
            "按键数": "84键(75%配列)",
            "按键类型": "Kailh矮轴(Cloud线性/Drift段落 可选)",
            "按键行程": "总程2.8mm/触发1.2mm",
            "按键寿命": "5000万次",
            "供电续航": "4500mAh"
          },
          "sell": "",
          "image": "images/akko-air01.avif",
          "source_url": "https://en.akkogear.com/product/air-01-low-profile-mechanical-keyboard/",
          "rating": null,
          "reviews": null,
          "launched": "2026"
        },
        {
          "brand": "NuPhy",
          "model": "Node75",
          "price": 469,
          "size": "317.1*137*1*22.4 mm",
          "weight": "659 g",
          "specs_detail": {
            "连接方式": "蓝牙5.0/2.4G/有线 三模",
            "按键数": "84键 75%配列",
            "按键类型": "矮轴,全键热插拔(45g红/50g茶/42g粉)",
            "按键行程": "—",
            "按键寿命": "—",
            "供电续航": "3000mAh,关灯约1000小时"
          },
          "sell": "",
          "image": "images/nuphy-node75.webp",
          "source_url": "https://nuphy.com/products/nuphy-node75-low-profile-wireless-mechanical-keyboard",
          "rating": null,
          "reviews": null,
          "launched": "2025"
        },
        {
          "brand": "AESCO",
          "model": "A83 Air",
          "price": 699,
          "size": "315*132*30 mm",
          "weight": "1030 g",
          "specs_detail": {
            "连接方式": "蓝牙5.0/2.4G/有线 三模",
            "按键数": "83键",
            "按键类型": "凯华定制全POM矮轴(薄荷轴)",
            "按键行程": "全程2.8mm/触发1.2mm",
            "按键寿命": "5000万次",
            "供电续航": "3800mAh,最长630小时"
          },
          "sell": "",
          "image": "images/aesco-a83-air.png",
          "source_url": "https://shop.rapoo.com/products/a83-air-backlit-mechanical-gaming-keyboard",
          "rating": null,
          "reviews": null,
          "launched": "2026"
        },
        {
          "brand": "洛斐 Lofree",
          "model": "小順 FLOW2",
          "price": 699,
          "size": "316.8*138*23.5 mm(84键)",
          "weight": "550 g(84键)",
          "specs_detail": {
            "连接方式": "蓝牙/2.4G/有线 三模",
            "按键数": "68/84/100键 可选",
            "按键类型": "凯华Cloud系列矮轴,热插拔/Gasket",
            "按键行程": "—",
            "按键寿命": "—",
            "供电续航": "3000mAh(84键)"
          },
          "sell": "",
          "image": "https://cdn.shopify.com/s/files/1/2779/9046/files/Flow2100_SpaceGray_PI01.png",
          "source_url": "https://www.lofree.co/products/flow-2-100-low-profile-mechanical-keyboard",
          "rating": null,
          "reviews": null,
          "launched": "2025"
        },
        {
          "brand": "NuPhy",
          "model": "Air96 V2",
          "price": 749,
          "size": "373.4×132.5×13.5 mm",
          "weight": "663 g",
          "specs_detail": {
            "连接方式": "蓝牙5.1/2.4G 1000Hz/有线 三模",
            "按键数": "100键(96%配列)",
            "按键类型": "Gateron KS-33矮轴(线性/段落 可选)",
            "按键行程": "总程3.2mm/触发1.2~1.8mm",
            "按键寿命": "—",
            "供电续航": "4000mAh,关灯最长220小时"
          },
          "sell": "",
          "image": "images/nuphy-air96-v2.jpg",
          "source_url": "https://nuphy.com/products/air96-v2",
          "rating": null,
          "reviews": null,
          "launched": "2024"
        },
        {
          "brand": "NuPhy",
          "model": "Kick75",
          "price": 799,
          "size": "333*143.3*33.6 mm",
          "weight": "877 g(矮軸)",
          "specs_detail": {
            "连接方式": "蓝牙5.0/2.4G/有线 三模",
            "按键数": "80键 ANSI 75%",
            "按键类型": "Nano矮轴/Max高轴,Gateron热插拔",
            "按键行程": "Nano矮轴总程3.5mm",
            "按键寿命": "—",
            "供电续航": "2500mAh,全灯关最长360小时"
          },
          "sell": "",
          "image": "images/nuphy-kick75.jpg",
          "source_url": "https://nuphy.com/products/kick75",
          "rating": null,
          "reviews": null,
          "launched": "2025"
        },
        {
          "brand": "MelGeek",
          "model": "O2 Mac版",
          "price": 899,
          "size": "326×135×27 mm",
          "weight": "650 g",
          "specs_detail": {
            "连接方式": "蓝牙5.3/2.4G/有线 三模",
            "按键数": "83键(75%配列,Mac布局)",
            "按键类型": "Kailh Sunlight矮轴(线性)",
            "按键行程": "总程2.8mm/触发1.2mm",
            "按键寿命": "—",
            "供电续航": "2500mAh,约7个月(日8h低功耗)"
          },
          "sell": "",
          "image": "https://cdn.shopify.com/s/files/1/0078/2863/5712/files/O2_for_Mac_keyboard.jpg",
          "source_url": "https://www.melgeek.com/products/o2-tri-mode-wireless-mechanical-keyboard",
          "rating": null,
          "reviews": null,
          "launched": "2025"
        }
      ]
    },
    "mouse": {
      "label": "垂直滑鼠",
      "spec_fields": [
        "连接方式",
        "分辨率DPI",
        "传感器",
        "手感",
        "滚轮",
        "颜色",
        "手型"
      ],
      "items": [
        {
          "brand": "英菲克 INPHIC",
          "model": "X9 Pro",
          "price": 129,
          "size": "124*78*74 mm",
          "weight": "95±5 g",
          "specs_detail": {
            "连接方式": "2.4G/蓝牙5.0/有线 三模",
            "分辨率DPI": "800-12000 DPI 多档",
            "传感器": "—",
            "手感": "垂直58°/人体工学/静音",
            "滚轮": "—",
            "颜色": "黑色/白色",
            "手型": "大手型"
          },
          "sell": "",
          "image": "images/inphic-x9pro.jpg",
          "source_url": "https://www.inphic.com/products/inphic-x9-pro-vertical-ergonomic-precision-dual-mouse",
          "rating": null,
          "reviews": null,
          "launched": null
        },
        {
          "brand": "B.O.W 航世",
          "model": "MD190L mini",
          "price": 159,
          "size": "72.28*76.42*120.24 mm",
          "weight": "—",
          "specs_detail": {
            "连接方式": "2.4G/蓝牙 双模",
            "分辨率DPI": "800/1200/1600/2400 DPI",
            "传感器": "—",
            "手感": "垂直/人体工学/静音",
            "滚轮": "3D防滑滚轮",
            "颜色": "—",
            "手型": "小手型"
          },
          "sell": "",
          "image": "images/bow-md190l-mini.jpg",
          "source_url": "https://detail.zol.com.cn/2112/2111827/param.shtml",
          "rating": null,
          "reviews": null,
          "launched": "2022"
        },
        {
          "brand": "雷柏 Rapoo",
          "model": "MV20",
          "price": 79,
          "size": "117*76*69 mm",
          "weight": "约90 g",
          "specs_detail": {
            "连接方式": "无线2.4G",
            "分辨率DPI": "800/1000/1200/1600 DPI",
            "传感器": "光学引擎",
            "手感": "垂直/人体工学",
            "滚轮": "—",
            "颜色": "商务黑",
            "手型": "大手型"
          },
          "sell": "",
          "image": "images/rapoo-mv20.png",
          "source_url": "https://www.rapoo.cn/product/589",
          "rating": null,
          "reviews": null,
          "launched": "2021"
        },
        {
          "brand": "羅技 Logitech",
          "model": "Lift",
          "price": 599,
          "size": "70*71*108 mm",
          "weight": "124 g",
          "specs_detail": {
            "连接方式": "蓝牙BLE + Logi Bolt 双模(3通道)",
            "分辨率DPI": "400-4000 DPI",
            "传感器": "Pluto One 光学",
            "手感": "57°垂直/人体工学(中小手)",
            "滚轮": "SmartWheel 智能滚轮",
            "颜色": "石墨黑/珍珠白/玫瑰粉",
            "手型": "中手型"
          },
          "sell": "",
          "image": "images/logitech-lift.png",
          "source_url": "https://www.logitech.com/zh-tw/products/mice/lift-vertical-ergonomic-mouse.html",
          "rating": null,
          "reviews": null,
          "launched": "2022"
        },
        {
          "brand": "多彩 Delux",
          "model": "M618XU",
          "price": 99,
          "size": "135.5*100*87 mm",
          "weight": "约225 g",
          "specs_detail": {
            "连接方式": "有线(USB)",
            "分辨率DPI": "最高4000 DPI",
            "传感器": "原相 PMW3610 光学",
            "手感": "垂直/人体工学",
            "滚轮": "—",
            "颜色": "—",
            "手型": "大手型"
          },
          "sell": "",
          "image": "images/delux-m618xu.jpg",
          "source_url": "https://www.deluxworld.com/pro-detail-M618X.html",
          "rating": null,
          "reviews": null,
          "launched": "2020"
        },
        {
          "brand": "綠聯 UGREEN",
          "model": "MU008",
          "price": 119,
          "size": "135*83*78 mm",
          "weight": "130 g(含电池)",
          "specs_detail": {
            "连接方式": "无线2.4G/蓝牙5.0 双模",
            "分辨率DPI": "1000/1600/2000/4000 DPI",
            "传感器": "3D光学传感器",
            "手感": "人体工学垂直(右手)",
            "滚轮": "有",
            "颜色": "黑色/灰色",
            "手型": "大手型"
          },
          "sell": "",
          "image": "images/ugreen-mu008.jpg",
          "source_url": "https://www.lulian.cn/product/1068.html",
          "rating": null,
          "reviews": null,
          "launched": "2022"
        },
        {
          "brand": "多彩 Delux",
          "model": "M618AIR GX",
          "price": 69,
          "size": "115*80.7*75.2 mm",
          "weight": "—",
          "specs_detail": {
            "连接方式": "无线2.4G(干电池版)",
            "分辨率DPI": "最高4000 DPI",
            "传感器": "—",
            "手感": "垂直/人体工学/静音(中小手)",
            "滚轮": "—",
            "颜色": "黑/樱花粉/薰衣紫/极地白/松叶绿",
            "手型": "中手型"
          },
          "sell": "",
          "image": "images/delux-m618air-gx.png",
          "source_url": "https://www.deluxworld.com/",
          "rating": null,
          "reviews": null,
          "launched": "2025"
        }
      ]
    }
  }
}
